<annotation>
	<folder>untied</folder>
	<filename>txofr.jpg</filename>
	<path>/home/an/shoeslace/dataset/train/txofr.jpg</path>
	<source>
		<database>Unknown</database>
	</source>
	<size>
		<width>320</width>
		<height>213</height>
		<depth>3</depth>
	</size>
	<segmented>0</segmented>
	<object>
		<name>untied_shoes</name>
		<pose>Unspecified</pose>
		<truncated>0</truncated>
		<difficult>0</difficult>
		<bndbox>
			<xmin>147</xmin>
			<ymin>39</ymin>
			<xmax>239</xmax>
			<ymax>197</ymax>
		</bndbox>
	</object>
	<object>
		<name>untied_shoes</name>
		<pose>Unspecified</pose>
		<truncated>0</truncated>
		<difficult>0</difficult>
		<bndbox>
			<xmin>28</xmin>
			<ymin>47</ymin>
			<xmax>148</xmax>
			<ymax>186</ymax>
		</bndbox>
	</object>
</annotation>
