<annotation>
	<folder>tied</folder>
	<filename>5nfrm.jpg</filename>
	<path>/home/an/shoeslace/dataset/train/5nfrm.jpg</path>
	<source>
		<database>Unknown</database>
	</source>
	<size>
		<width>500</width>
		<height>439</height>
		<depth>3</depth>
	</size>
	<segmented>0</segmented>
	<object>
		<name>tied_shoes</name>
		<pose>Unspecified</pose>
		<truncated>0</truncated>
		<difficult>0</difficult>
		<bndbox>
			<xmin>278</xmin>
			<ymin>140</ymin>
			<xmax>457</xmax>
			<ymax>413</ymax>
		</bndbox>
	</object>
	<object>
		<name>tied_shoes</name>
		<pose>Unspecified</pose>
		<truncated>0</truncated>
		<difficult>0</difficult>
		<bndbox>
			<xmin>18</xmin>
			<ymin>3</ymin>
			<xmax>267</xmax>
			<ymax>398</ymax>
		</bndbox>
	</object>
</annotation>
